pytermtalk_ref/__init__.py
pytermtalk_ref/chat.py
pytermtalk_ref-1.1.1.dist-info/WHEEL
pytermtalk_ref-1.1.1.dist-info/entry_points.txt
pytermtalk_ref-1.1.1.dist-info/METADATA
pytermtalk_ref-1.1.1.dist-info/RECORD
