Metadata-Version: 2.4
Name: pytermtalk-ref
Version: 1.1.1
Summary: My reference implementation of a terminal-based chat program using sockets; supports both client and server modes.
Keywords: chat,terminal,cli,client & server,reference
Author: Rik Roos
Author-email: Rik Roos <28710055+GuzziRik@users.noreply.github.com>
License-Expression: MIT
Classifier: Programming Language :: Python :: 3
Classifier: Programming Language :: Python :: 3.10
Classifier: License :: OSI Approved :: MIT License
Classifier: Intended Audience :: Developers
Classifier: Topic :: Software Development
Classifier: Topic :: Communications :: Chat
Classifier: Operating System :: OS Independent
Requires-Python: >=3.10
Project-URL: Documentation, https://github.com/RikRoos/pytermtalk-ref/blob/master/README.md
Project-URL: Homepage, https://github.com/RikRoos/pytermtalk-ref
Project-URL: Source, https://github.com/RikRoos/pytermtalk-ref/tree/master/src/pytermtalk_ref
